{
	"class" : {
		"on:" : " 7/23/2018 10:01:09",
		"onStream:" : " 7/23/2018 10:01:09",
		"parsePackets:" : " 7/23/2018 10:01:09" },
	"instance" : {
		"atEnd" : " 7/23/2018 10:01:09",
		"binary" : " 7/23/2018 10:01:09",
		"close" : " 7/23/2018 10:01:09",
		"mpisUpToEnd" : " 7/23/2018 10:01:09",
		"next" : " 7/23/2018 10:01:09",
		"next:" : " 7/23/2018 10:01:09",
		"nextMPI" : " 7/23/2018 10:01:09",
		"nextNewFormatPacketLength" : " 7/23/2018 10:01:09",
		"nextNumber:" : " 7/23/2018 10:01:09",
		"nextPacket" : " 7/23/2018 10:01:09",
		"nextPacketsUpToEnd" : " 7/23/2018 10:01:09",
		"nextS2KSpecifier" : " 7/23/2018 10:01:09",
		"nextSubpacketData" : " 7/23/2018 10:01:09",
		"on:" : " 7/23/2018 10:01:09" } }
