{
	"class" : {
		 },
	"instance" : {
		"bulkCipherDictionary" : " 7/23/2018 10:01:29",
		"computeSecret" : " 7/23/2018 10:01:29",
		"finishedMsgForClient" : " 7/23/2018 10:01:29",
		"finishedMsgForServer" : " 7/23/2018 10:01:29",
		"generateKeyBlock" : " 7/23/2018 10:01:29",
		"hashFinishedMsgsForClient" : " 7/23/2018 10:01:29",
		"hashFinishedMsgsForServer" : " 7/23/2018 10:01:29",
		"hashFinishedMsgsWithLabel:" : " 7/23/2018 10:01:29",
		"installKeyWithCipherReadKey:cipherWriteKey:macReadKey:macWriteKey:" : " 7/23/2018 10:01:29",
		"installKeysFromKeyBlock:" : " 7/23/2018 10:01:29",
		"macDictionary" : " 7/23/2018 10:01:29",
		"verifyFinishedMsgForClient:" : " 7/23/2018 10:01:29",
		"verifyFinishedMsgForServer:" : " 7/23/2018 10:01:29" } }
